graph_structures/__init__.py
graph_structures/unweighted_graph.py
hash_structure/__init__.py
hash_structure/hash.py
linked_lists_structures/__init__.py
linked_lists_structures/linked_list.py
queves_structures/__init__.py
queves_structures/queve_deque.py
queves_structures/queve_exceptions.py
queves_structures/queve_list.py
queves_structures/queve_queve.py
queves_structures/queves_test.py
sets_structures/__init__.py
sets_structures/disjoint_sets.py
stacks_structures/__init__.py
stacks_structures/stack_deque.py
stacks_structures/stack_exceptions.py
stacks_structures/stack_lifo_queve.py
stacks_structures/stack_list.py
tree_structures/AVL_tree.py
tree_structures/BST_tree.py
tree_structures/__init__.py
tree_structures/heap.py
DIDACTIC_WADDLE_odob-0.1.0.dist-info/LICENSE
DIDACTIC_WADDLE_odob-0.1.0.dist-info/METADATA
DIDACTIC_WADDLE_odob-0.1.0.dist-info/WHEEL
DIDACTIC_WADDLE_odob-0.1.0.dist-info/top_level.txt
DIDACTIC_WADDLE_odob-0.1.0.dist-info/RECORD
